whappy/__init__.py
whappy/api.py
whappy-0.2.1.dist-info/METADATA
whappy-0.2.1.dist-info/WHEEL
whappy-0.2.1.dist-info/top_level.txt
whappy-0.2.1.dist-info/RECORD
